climage/__init__.py
climage/__main__.py
climage/__version__.py
climage/climage.py
climage-0.2.1.dist-info/LICENSE
climage-0.2.1.dist-info/METADATA
climage-0.2.1.dist-info/WHEEL
climage-0.2.1.dist-info/entry_points.txt
climage-0.2.1.dist-info/top_level.txt
climage-0.2.1.dist-info/RECORD
