Metadata-Version: 2.1
Name: climage
Version: 0.2.1
Summary: Convert images to beautiful ANSI escape codes
Author-email: Patrick Nappa <patricknappa@gmail.com>
License: MIT License
Project-URL: Documentation, http://github.com/pnappa/CLImage
Project-URL: Issues, http://github.com/pnappa/CLImage/issues
Project-URL: Source, http://github.com/pnappa/CLImage
Classifier: Development Status :: 4 - Beta
Classifier: Environment :: Console
Classifier: Intended Audience :: Developers
Classifier: License :: OSI Approved :: MIT License
Classifier: Operating System :: OS Independent
Classifier: Programming Language :: Python
Classifier: Programming Language :: Python :: 3 :: Only
Classifier: Programming Language :: Python :: 3.2
Classifier: Programming Language :: Python :: 3.3
Classifier: Programming Language :: Python :: 3.4
Classifier: Programming Language :: Python :: 3.5
Classifier: Programming Language :: Python :: 3.6
Classifier: Programming Language :: Python :: 3.7
Classifier: Programming Language :: Python :: 3.8
Classifier: Topic :: Artistic Software
Classifier: Topic :: Multimedia :: Graphics
Classifier: Topic :: System :: System Shells
Classifier: Topic :: Utilities
Requires-Python: >=3.2
License-File: LICENSE
Requires-Dist: Pillow
Requires-Dist: kdtree
